XStatic_Json2yaml-0.1.1.0-py2.7-nspkg.pth
XStatic_Json2yaml-0.1.1.0.dist-info/METADATA
XStatic_Json2yaml-0.1.1.0.dist-info/RECORD
XStatic_Json2yaml-0.1.1.0.dist-info/WHEEL
XStatic_Json2yaml-0.1.1.0.dist-info/namespace_packages.txt
XStatic_Json2yaml-0.1.1.0.dist-info/top_level.txt
xstatic/pkg/json2yaml/__init__.py
xstatic/pkg/json2yaml/data/json2yaml.js
