Metadata-Version: 2.1
Name: XStatic-Json2yaml
Version: 0.1.1.0
Summary: Json2yaml 0.1.1 (XStatic packaging standard)
Home-page: https://github.com/jeffsu/json2yaml
Maintainer: xinni.ge
Maintainer-email: xinni.ge@ntt.com
License: MIT
Keywords: json2yaml xstatic
Platform: any
